{
	"pages": [ //pages数组中第一项表示应用启动页，参考：https://uniapp.dcloud.io/collocation/pages
		{
			"path": "pages/index/index",
			"style": {
				"enablePullDownRefresh": true,
				"navigationStyle": "custom",
				"onReachBottomDistance": 150,
				// "titleNView":false,
				"navigationBarTextStyle": "white",
				"app-plus": {
					"animationType": "zoom-fade-out",
					"animationDuration": 300
				}
			}
		},
		{
			"path": "pages/zadopt/adopt",
			"style": {
				"navigationStyle": "custom"
				// "titleNView":true
			}
		},
		{
			"path": "pages/zadopt/setup",
			"style": {
				"navigationStyle": "custom"
				// "titleNView":true

			}
		},
		{
			"path": "pages/askdoc/askdoc",
			"style": {
				// "navigationStyle": "custom"
			}
		},

		// 登陆模块
		{
			"path": "pages/login/login",
			"style": {
				"navigationStyle": "custom"
			}
		},

		// 二级页面
		{
			"path": "pages/profile/SecondPages/Setting",
			"style": {
				"navigationStyle": "custom"
			}
		},
		{
			"path": "pages/sameCity/SecondPages/ShopDetail",
			"style": {
				"navigationStyle": "custom"
			}
		},
		
		{
			"path": "pages/profile/SecondPages/MyOrder",
			"style": {
				"navigationStyle": "custom"
			}
		},
		{
			"path": "pages/profile/SecondPages/wodefabu",
			"style": {
				"navigationStyle": "custom"
				// "titleNView":true
			}
		},
			// 收藏页面
		{
			"path": "pages/profile/SecondPages/Favorite",
			"style": {
				"navigationStyle": "custom"
			}
		},
			// 宠物领养详情
		{
			"path": "pages/zadopt/petdetail",
			"style": {
				"navigationStyle": "custom"
			}
		},
			// 文章详情
		{
			"path": "pages/article/articlesDetail",
			"style": {
				"navigationStyle": "custom"
			}
		},

		// tabbar页面
		{
			"path": "pages/index/index",
			"style": {
				"navigationStyle": "custom"
				// "titleNView":true
			}
		},
		{
			"path": "pages/sameCity/sameCity",
			"style": {
				"navigationStyle": "custom"
				// "titleNView":true
			}
		},
		{
			"path": "pages/petquan/petquan",
			"style": {
				"navigationStyle": "custom"
				// "titleNView":true
			}
		},
		{
			"path": "pages/profile/profile",
			"style": {
				"navigationStyle": "custom"
				// "titleNView":true
			}
		},
		{
		"path": "pages/profile/profile",
		"style": {
			"navigationStyle": "custom"
			// "titleNView":true
		}
	}

],
"tabBar": {
	"color": "#7A7E83",
	"selectedColor": "#FFB600",
	"borderStyle": "black",
	"backgroundColor": "#ffffff",
	"list": [{
			"pagePath": "pages/index/index",
			"selectedIconPath": "static/icon/tabbar/pets.png",
			"iconPath": "static/icon/tabbar/pets.png",
			"text": "首页"
		},
		{
			"pagePath": "pages/sameCity/sameCity",
			"selectedIconPath": "static/icon/tabbar/suozaichengshi.png",
			"iconPath": "static/icon/tabbar/suozaichengshi.png",
			"text": "同城"
		},
		{
			"pagePath": "pages/petquan/petquan",
			"selectedIconPath": "static/icon/tabbar/social.png",
			"iconPath": "static/icon/tabbar/social.png",
			"text": "宠圈"
		},
		{
			"pagePath": "pages/profile/profile",
			"selectedIconPath": "static/icon/tabbar/user.png",
			"iconPath": "static/icon/tabbar/user.png",
			"text": "我的"
		}
	]

},
"globalStyle": {
	"navigationBarTextStyle": "black",
	"navigationBarTitleText": "uni-app",
	"navigationBarBackgroundColor": "#F8F8F8",
	"backgroundColor": "#F8F8F8",
	"onReachBottomDistance": 150
},
"uniIdRouter": {}
}
